web360/__init__.py
web360/jobs.py
web360/logger.py
web360/main.py
web360/tools/__init__.py
web360/tools/email.py
web360/tools/memory.py
web360/tools/web.py
web360-0.1.3.dist-info/LICENSE
web360-0.1.3.dist-info/METADATA
web360-0.1.3.dist-info/WHEEL
web360-0.1.3.dist-info/RECORD
