Metadata-Version: 2.3
Name: web360
Version: 0.1.3
Summary: Tools for AI Agents
License: MIT
Author: Lukas Korganas
Requires-Python: >=3.10,<3.13
Classifier: License :: OSI Approved :: MIT License
Classifier: Programming Language :: Python :: 3
Classifier: Programming Language :: Python :: 3.10
Classifier: Programming Language :: Python :: 3.11
Classifier: Programming Language :: Python :: 3.12
Requires-Dist: build (>=1.2.2.post1,<2.0.0)
Requires-Dist: dspy (>=2.6.6,<3.0.0)
Requires-Dist: rank-bm25 (>=0.2.2,<0.3.0)
Requires-Dist: twine (>=6.1.0,<7.0.0)
